StrangeSerializerLab3
StrangeSerializerLab3/StrangeJSON
StrangeSerializerLab3/StrangeXML
